telemongo/__init__.py
telemongo/telemongo.py
telemongo-0.2.2.dist-info/LICENSE
telemongo-0.2.2.dist-info/METADATA
telemongo-0.2.2.dist-info/WHEEL
telemongo-0.2.2.dist-info/RECORD
